psgshortcut/LICENSE.txt
psgshortcut/README.md
psgshortcut/__init__.py
psgshortcut/__main__.py
psgshortcut/psgshortcut.ico
psgshortcut/psgshortcut.py
psgshortcut/screenshot.png
psgshortcut-5.0.0.dist-info/LICENSE.txt
psgshortcut-5.0.0.dist-info/METADATA
psgshortcut-5.0.0.dist-info/WHEEL
psgshortcut-5.0.0.dist-info/entry_points.txt
psgshortcut-5.0.0.dist-info/top_level.txt
psgshortcut-5.0.0.dist-info/RECORD
