Metadata-Version: 2.1
Name: psgshortcut
Version: 5.0.0
Summary: Utility made with PySimpleGUI to create shortcuts of files or programs
Home-page: https://github.com/PySimpleGUI/psgshortcut
Author: PySimpleSoft Inc.
License: Free To Use But Restricted
Keywords: GUI UI PySimpleGUI tkinter psgshortcut shortcut windows taskbar
Classifier: Intended Audience :: Developers
Classifier: License :: Free To Use But Restricted
Classifier: Operating System :: OS Independent
Classifier: Framework :: PySimpleGUI
Classifier: Framework :: PySimpleGUI :: 5
Classifier: Programming Language :: Python :: 3
Classifier: Programming Language :: Python :: 3.6
Classifier: Programming Language :: Python :: 3.7
Classifier: Programming Language :: Python :: 3.8
Classifier: Programming Language :: Python :: 3.9
Classifier: Programming Language :: Python :: 3.10
Classifier: Programming Language :: Python :: 3.11
Classifier: Programming Language :: Python :: 3.12
Classifier: Programming Language :: Python :: 3.13
Classifier: Topic :: Multimedia :: Graphics
Requires-Python: >=3.6
License-File: LICENSE.txt
Requires-Dist: PySimpleGUI >=5
Requires-Dist: pywin32
